inline_labels.py
matplotlib_inline_labels-0.2.1.dist-info/LICENSE
matplotlib_inline_labels-0.2.1.dist-info/WHEEL
matplotlib_inline_labels-0.2.1.dist-info/METADATA
matplotlib_inline_labels-0.2.1.dist-info/RECORD
