Metadata-Version: 2.1
Name: matplotlib_inline_labels
Version: 0.2.1
Summary: Inline line labels for matplotlib with automatic positionning
Author-email: mathieu17g <mathieu19g@icloud.com>
Requires-Python: >=3.12
Classifier: Programming Language :: Python :: 3
Classifier: License :: OSI Approved :: MIT License
Classifier: Framework :: Matplotlib
Classifier: Operating System :: OS Independent
Classifier: Development Status :: 3 - Alpha
Requires-Dist: matplotlib>=3.8
Requires-Dist: nptyping>=2.5
Requires-Dist: numpy>=1.26
Requires-Dist: Shapely>=2.0
Requires-Dist: tqdm>=4.66
Requires-Dist: pymoo>=0.6
Requires-Dist: pytest>=8 ; extra == "test"
Requires-Dist: pytest-cov>=5 ; extra == "test"
Requires-Dist: pytest-mpl>=0.17 ; extra == "test"
Requires-Dist: pytest-xdist>=3.5 ; extra == "test"
Requires-Dist: scipy>=1.12 ; extra == "test"
Project-URL: Bug Tracker, https://github.com/mathieu17g/matplotlib_inline_labels/issues
Project-URL: Homepage, https://github.com/mathieu17g/matplotlib_inline_labels
Provides-Extra: test
